MANIFEST.in
README
README.rst
changes.rst
setup.py
gap/__init__.py
gap/conf.py
gap/template.py
gap/views.py
gap.egg-info/PKG-INFO
gap.egg-info/SOURCES.txt
gap.egg-info/dependency_links.txt
gap.egg-info/not-zip-safe
gap.egg-info/top_level.txt
gap/bin/gap
gap/templates/.gitignore
gap/templates/requirements.gip
gap/templates/.tmp/.gitignore
gap/templates/bin/.gip.swp
gap/templates/bin/.ipython.py.swp
gap/templates/bin/gip
gap/templates/bin/install.sh
gap/templates/bin/ipython.py
gap/templates/bin/ipython.pyc
gap/templates/bin/run
gap/templates/bin/shell
gap/templates/module/__init__.py
gap/templates/module/__init__.pyc
gap/templates/module/models.py
gap/templates/module/models.pyc
gap/templates/module/routes.py
gap/templates/module/routes.pyc
gap/templates/module/views.py
gap/templates/module/views.pyc
gap/templates/src/app.yaml
gap/templates/src/config.py
gap/templates/src/config.pyc
gap/templates/src/routes.py
gap/templates/src/routes.pyc
gap/templates/src/app/__init__.py
gap/templates/src/app/__init__.pyc
gap/templates/src/lib/.gitignore
gap/templates/src/lib/__init__.py
gap/templates/src/lib/__init__.pyc
gap/templates/src/static/logo.png
gap/templates/src/templates/homepage.html
gap/templates/tests/README.md
gap/templates/tests/__init__.py
gap/templates/tests/__init__.pyc
gap/templates/tests/nose.cfg
gap/templates/tests/requirements.pip
gap/templates/tests/run_tests.py
gap/templates/tests/run_tests.pyc
gap/templates/tests/test_myapp.py
gap/templates/tests/test_myapp.pyc
gap/templates/tests/test_settings.py
gap/templates/tests/test_settings.pyc
gap/templates/tests/test_webapp.py
gap/templates/tests/test_webapp.pyc
gap/utils/__init__.py
gap/utils/decorators.py
gap/utils/defer.py
gap/utils/gip.py
gap/utils/imports.py
gap/utils/routes.py
gap/utils/setup.py
gap/utils/tests.py