Metadata-Version: 1.1
Name: gap
Version: 0.4.9.1
Summary: Google App Engine project bootstrap
Home-page: https://github.com/czervenka/gap
Author: Robin Gottfried
Author-email: google@kebet.cz
License: Apache License 2.0
Platform: UNKNOWN
Requires: pip
